simple_css_selector_transform/__init__.py
simple_css_selector_transform/_css_utils.py
simple_css_selector_transform/app.py
simple_css_selector_transform/rewrite.py
simple_css_selector_transform-0.1.0.dist-info/LICENSE
simple_css_selector_transform-0.1.0.dist-info/METADATA
simple_css_selector_transform-0.1.0.dist-info/WHEEL
simple_css_selector_transform-0.1.0.dist-info/entry_points.txt
simple_css_selector_transform-0.1.0.dist-info/RECORD
