Metadata-Version: 2.1
Name: simple-css-selector-transform
Version: 0.1.0
Summary: Simple transformations for CSS Selectors
Home-page: https://github.com/StreamHPC/simple-css-selector-transform
License: MIT
Keywords: python,css,transform,rewrite,doxysphinx,doxygen,sphinx
Author: Stream HPC B.V.
Author-email: gergely@streamhpc.com
Requires-Python: >=3.8,<4.0
Classifier: Development Status :: 2 - Pre-Alpha
Classifier: Environment :: Console
Classifier: Intended Audience :: Developers
Classifier: License :: OSI Approved :: MIT License
Classifier: Operating System :: OS Independent
Classifier: Programming Language :: Python :: 3
Classifier: Programming Language :: Python :: 3.8
Classifier: Programming Language :: Python :: 3.9
Classifier: Programming Language :: Python :: 3.10
Classifier: Programming Language :: Python :: 3.11
Classifier: Programming Language :: Python :: 3
Classifier: Programming Language :: Python :: 3.8
Classifier: Topic :: Software Development :: Libraries :: Python Modules
Classifier: Typing :: Typed
Requires-Dist: tinycss2 (>=1.2.1,<2.0.0)
Requires-Dist: typer (>=0.7.0,<0.8.0)
Requires-Dist: webencodings (>=0.5.1,<0.6.0)
Project-URL: Repository, https://github.com/StreamHPC/simple-css-selector-transform
